<?xml version="1.0" encoding="UTF-8"?>
<root
    xmlns:xsi="http://www.w3.org/2001/XMLSchema-instance"
    xmlns="roeststoff"
    xsi:schemaLocation="roeststoff ../schemas/restaurants.xsd">
    <restaurant>
        <name>KOMU</name>
        <description></description>
        <image>images/restaurants/komu.svg</image>
        <team>
            <member>Christoph Kunz</member>
        </team>
        <appearances>
            <appearance>
                <episode>41</episode>
                <episodeTime>00:00</episodeTime>
            </appearance>
        </appearances>
    </restaurant>
    <restaurant>
        <name>Ember</name>
        <description>Open Fire Cooking</description>
        <image>images/restaurants/ember.svg</image>
        <appearances>
            <appearance>
                <episode>40</episode>
                <episodeTime>38:21</episodeTime>
            </appearance>
        </appearances>
    </restaurant>
    <restaurant>
        <name>Posthotel</name>
        <image>images/restaurants/posthotel.webp</image>
        <appearances>
            <appearance>
                <episode>39</episode>
                <episodeTime>23:17</episodeTime>
            </appearance>
        </appearances>
        <characteristics>
            <characteristic>
                <episode>39</episode>
                <episodeTime>37:33</episodeTime>
                <description>ganz weit oben in der La Liste</description>
            </characteristic>
            <characteristic>
                <episode>39</episode>
                <episodeTime>37:05</episodeTime>
                <description>hat 3 Sterne seid vielen Jahren</description>
            </characteristic>
        </characteristics>
    </restaurant>
    <restaurant>
        <name>Butterhandlung</name>
        <image>images/restaurants/butterhandlung.jpg</image>
        <appearances>
            <appearance>
                <episode>38</episode>
                <episodeTime>1:06:26</episodeTime>
            </appearance>
        </appearances>
    </restaurant>
    <restaurant>
        <name>Pars Pralinen</name>
        <description>Handgemachte Pralinen als Kunststücke.</description>
        <image>images/misc/pars_pralinen.webp</image>
        <appearances>
            <appearance>
                <episode>35</episode>
                <episodeTime>7:04</episodeTime>
            </appearance>
        </appearances>
    </restaurant>
    <restaurant>
        <name>El Califa de León</name>
        <image>images/restaurants/el_califa_de_leon.jpg</image>
        <appearances>
            <appearance>
                <episode>34</episode>
                <episodeTime>1:37:05</episodeTime>
            </appearance>
        </appearances>
    </restaurant>
    <restaurant>
        <name>Big Window</name>
        <image>images/restaurants/big_window.png</image>
        <appearances>
            <appearance>
                <episode>34</episode>
                <episodeTime>1:19:35</episodeTime>
            </appearance>
        </appearances>
    </restaurant>
    <restaurant>
        <name>Rubens</name>
        <image>images/restaurants/rubens.png</image>
        <appearances>
            <appearance>
                <episode>34</episode>
                <episodeTime>34:25</episodeTime>
            </appearance>
        </appearances>
        <characteristics>
            <characteristic>
                <episode>34</episode>
                <episodeTime>36:02</episodeTime>
                <description>Lieblingsrestaurant von Christian Stachelhaus (laut Peter Smits)</description>
            </characteristic>
        </characteristics>
    </restaurant>
    <restaurant>
        <name>Smitty's Market</name>
        <image>images/restaurants/smittys_market.jpg</image>
        <appearances>
            <appearance>
                <episode>30</episode>
                <episodeTime>2:13:35</episodeTime>
            </appearance>
        </appearances>
    </restaurant>
    <restaurant>
        <name>Neptune</name>
        <description>Restaurant im All</description>
        <image></image>
        <appearances>
            <appearance>
                <episode>29</episode>
                <episodeTime>33:48</episodeTime>
            </appearance>
        </appearances>
    </restaurant>
    <restaurant>
        <name>Zum heiligen Teufel</name>
        <image>images/restaurants/zum_heiligen_teufel.png</image>
        <appearances>
            <appearance>
                <episode>29</episode>
                <episodeTime>30:55</episodeTime>
            </appearance>
        </appearances>
    </restaurant>
    <restaurant>
        <name>Lohninger</name>
        <image>images/restaurants/lohninger.png</image>
        <appearances>
            <appearance>
                <episode>29</episode>
                <episodeTime>14:05</episodeTime>
            </appearance>
        </appearances>
    </restaurant>
    <restaurant>
        <name>Bareiss</name>
        <image>images/restaurants/bareiss.webp</image>
        <appearances>
            <appearance>
                <episode>28</episode>
                <episodeTime>2:51:48</episodeTime>
            </appearance>
        </appearances>
    </restaurant>
    <restaurant>
        <name>Tante Fichte</name>
        <image>images/restaurants/tante_fichte.png</image>
        <team>
            <member>Michael Köhle</member>
        </team>
        <appearances>
            <appearance>
                <episode>28</episode>
                <episodeTime>1:38:30</episodeTime>
            </appearance>
        </appearances>
    </restaurant>
    <restaurant>
        <name>DAR</name>
        <image>images/restaurants/dar.png</image>
        <appearances>
            <appearance>
                <episode>28</episode>
                <episodeTime>1:13:36</episodeTime>
            </appearance>
        </appearances>
    </restaurant>
    <restaurant>
        <name>Brikz</name>
        <image>images/restaurants/brikz.jpg</image>
        <team>
            <member>Arne Anker</member>
        </team>
        <appearances>
            <appearance>
                <episode>27</episode>
                <episodeTime>1:23:00</episodeTime>
            </appearance>
        </appearances>
    </restaurant>
    <restaurant>
        <name>Hafenküche</name>
        <image>images/restaurants/hafenkueche.svg</image>
        <team>
            <member>Mathias Brandweiner</member>
        </team>
        <appearances>
            <appearance>
                <episode>25</episode>
                <episodeTime>3:20:45</episodeTime>
            </appearance>
        </appearances>
    </restaurant>
    <restaurant>
        <name>Showroom</name>
        <image>images/restaurants/showroom.jpg</image>
        <team>
            <member>Dominik Keppler</member>
        </team>
        <appearances>
            <appearance>
                <episode>36</episode>
                <episodeTime>28:30</episodeTime>
            </appearance>
            <appearance>
                <episode>24</episode>
                <episodeTime>2:31:15</episodeTime>
            </appearance>
            <appearance>
                <episode>24</episode>
                <episodeTime>1:43:15</episodeTime>
            </appearance>
        </appearances>
    </restaurant>
    <restaurant>
        <name>Les Valseuse</name>
        <image>images/restaurants/les_valseuse.jpg</image>
        <appearances>
            <appearance>
                <episode>24</episode>
                <episodeTime>25:50</episodeTime>
            </appearance>
        </appearances>
    </restaurant>
    <restaurant>
        <name>Gästehaus Klaus Erfort</name>
        <image>images/restaurants/klaus_erfort.svg</image>
        <appearances>
            <appearance>
                <episode>23</episode>
                <episodeTime>3:49:07</episodeTime>
            </appearance>
        </appearances>
    </restaurant>
    <restaurant>
        <name>Steirereck</name>
        <image>images/restaurants/steirereck.jpg</image>
        <appearances>
            <appearance>
                <episode>23</episode>
                <episodeTime>3:42:38</episodeTime>
            </appearance>
        </appearances>
    </restaurant>
    <restaurant>
        <name>Fischers Fritz Berlin</name>
        <image>images/restaurants/fischers_fritz.png</image>
        <appearances>
            <appearance>
                <episode>23</episode>
                <episodeTime>3:41:40</episodeTime>
            </appearance>
        </appearances>
    </restaurant>
    <restaurant>
        <name>Henne Kirkeby Kro</name>
        <image>images/restaurants/henne_kirkeby_kro.jpg</image>
        <appearances>
            <appearance>
                <episode>23</episode>
                <episodeTime>3:40:00</episodeTime>
            </appearance>
        </appearances>
    </restaurant>
    <restaurant>
        <name>Ikarus - Hangar-7</name>
        <image>images/restaurants/ikarus_hangar_7.png</image>
        <appearances>
            <appearance>
                <episode>23</episode>
                <episodeTime>3:39:13</episodeTime>
            </appearance>
        </appearances>
    </restaurant>
    <restaurant>
        <name>Pakta</name>
        <image>images/restaurants/pakta.jpg</image>
        <appearances>
            <appearance>
                <episode>23</episode>
                <episodeTime>3:37:35</episodeTime>
            </appearance>
        </appearances>
    </restaurant>
    <restaurant>
        <name>The Oberoi Beach Resort Mauritius</name>
        <image>images/restaurants/oberoi_mauritius.png</image>
        <appearances>
            <appearance>
                <episode>19</episode>
                <episodeTime>3:30</episodeTime>
            </appearance>
        </appearances>
    </restaurant>
    <restaurant>
        <name>SodaZitron</name>
        <image>images/restaurants/sodazitron.jpg</image>
        <appearances>
            <appearance>
                <episode>18</episode>
                <episodeTime>3:20:52</episodeTime>
            </appearance>
        </appearances>
    </restaurant>
    <restaurant>
        <name>La Societe</name>
        <image>images/restaurants/la_societe.png</image>
        <appearances>
            <appearance>
                <episode>31</episode>
                <episodeTime>1:42:03</episodeTime>
            </appearance>
            <appearance>
                <episode>18</episode>
                <episodeTime>19:24</episodeTime>
            </appearance>
        </appearances>
    </restaurant>
    <restaurant>
        <name>Kölner Wasserturm</name>
        <image>images/restaurants/wasserturm_koeln.svg</image>
        <appearances>
            <appearance>
                <episode>18</episode>
                <episodeTime>18:40</episodeTime>
            </appearance>
        </appearances>
    </restaurant>
    <restaurant>
        <name>Gasthaus Assenmacher</name>
        <image>images/restaurants/assenmacher_gasthaus.png</image>
        <appearances>
            <appearance>
                <episode>18</episode>
                <episodeTime>9:45</episodeTime>
            </appearance>
        </appearances>
        <characteristics>
            <characteristic>
                <episode>18</episode>
                <episodeTime>9:45</episodeTime>
                <description>hat Bib Gourmand</description>
            </characteristic>
        </characteristics>
    </restaurant>
    <restaurant>
        <name>Jordnær</name>
        <image>images/restaurants/jordaer.png</image>
        <appearances>
            <appearance>
                <episode>17</episode>
                <episodeTime>50:30</episodeTime>
            </appearance>
        </appearances>
    </restaurant>
    <restaurant>
        <name>Alchemist</name>
        <image>images/restaurants/alchemist.png</image>
        <appearances>
            <appearance>
                <episode>17</episode>
                <episodeTime>50:30</episodeTime>
            </appearance>
        </appearances>
    </restaurant>
    <restaurant>
        <name>Dachgarten-Restaurant</name>
        <description>Restaurant im Bundestag</description>
        <image>images/restaurants/dachgarten.png</image>
        <appearances>
            <appearance>
                <episode>16</episode>
                <episodeTime>1:52:20</episodeTime>
            </appearance>
        </appearances>
        <characteristics>
            <characteristic>
                <episode>16</episode>
                <episodeTime>1:55:03</episodeTime>
                <description>nur deutscher Wein</description>
            </characteristic>
        </characteristics>
    </restaurant>
    <restaurant>
        <name>Rutz</name>
        <image>images/restaurants/rutz.png</image>
        <team>
            <member>Nancy Großmann</member>
        </team>
        <appearances>
            <appearance>
                <episode>32</episode>
                <episodeTime>1:41:32</episodeTime>
            </appearance>
            <appearance>
                <episode>16</episode>
                <episodeTime>1:32:15</episodeTime>
            </appearance>
        </appearances>
        <characteristics>
            <characteristic>
                <episode>16</episode>
                <episodeTime>1:32:15</episodeTime>
                <description>3 Sterne</description>
            </characteristic>
        </characteristics>
    </restaurant>
    <restaurant>
        <name>Chef's Table at Brooklyn Fare</name>
        <image>images/restaurants/chefs_table_brooklyn_fare.png</image>
        <appearances>
            <appearance>
                <episode>15</episode>
                <episodeTime>44:55</episodeTime>
            </appearance>
        </appearances>
        <characteristics>
            <characteristic>
                <episode>15</episode>
                <episodeTime>45:50</episodeTime>
                <description>hat 3 Sterne</description>
            </characteristic>
        </characteristics>
    </restaurant>
    <restaurant>
        <name>AURA</name>
        <description>von Alexander Herrmann und Tobias Baetz</description>
        <image>images/restaurants/aura_alexander_herrmann_tobias_baetz.svg</image>
        <team>
            <member>Alexander Herrmann</member>
            <member>Tobias Baetz</member>
        </team>
        <appearances>
            <appearance>
                <episode>12</episode>
                <episodeTime>2:44</episodeTime>
            </appearance>
        </appearances>
    </restaurant>
    <restaurant>
        <name>Epicure (Paris)</name>
        <image>images/restaurants/epicure_paris.jpg</image>
        <appearances>
            <appearance>
                <episode>11</episode>
                <episodeTime>54:05</episodeTime>
            </appearance>
        </appearances>
    </restaurant>
    <restaurant>
        <name>Schwerelos (Dresden)</name>
        <description>Das Achterbahnrestaurant</description>
        <image>images/restaurants/schwerelos_dresden.png</image>
        <appearances>
            <appearance>
                <episode>11</episode>
                <episodeTime>24:50</episodeTime>
            </appearance>
        </appearances>
    </restaurant>
    <restaurant>
        <name>Jardin de Sens</name>
        <image>images/restaurants/jardin_des_sens.svg</image>
        <appearances>
            <appearance>
                <episode>9</episode>
                <episodeTime>2:19:05</episodeTime>
            </appearance>
        </appearances>
        <characteristics>
            <characteristic>
                <episode>9</episode>
                <episodeTime>2:23:15</episodeTime>
                <description>deutsch: Garten der Sinne</description>
            </characteristic>
        </characteristics>
    </restaurant>
    <restaurant>
        <name>Jan</name>
        <image>images/restaurants/jan_hartwig.png</image>
        <appearances>
            <appearance>
                <episode>36</episode>
                <episodeTime>3:00</episodeTime>
            </appearance>
            <appearance>
                <episode>9</episode>
                <episodeTime>1:33:53</episodeTime>
            </appearance>
        </appearances>
    </restaurant>
    <restaurant>
        <name>Irma la Douce</name>
        <image>images/restaurants/irma_la_douce.jpg</image>
        <appearances>
            <appearance>
                <episode>9</episode>
                <episodeTime>1:14:15</episodeTime>
            </appearance>
        </appearances>
    </restaurant>
    <restaurant>
        <name>CODA</name>
        <description>Fine Dining mit ausschließlich Desserts und Cocktails</description>
        <image>images/restaurants/coda_berlin.svg</image>
        <team>
            <member>René Frank</member>
        </team>
        <appearances>
            <appearance>
                <episode>26</episode>
                <episodeTime>1:58:25</episodeTime>
            </appearance>
            <appearance>
                <episode>9</episode>
                <episodeTime>00:06:25</episodeTime>
            </appearance>
        </appearances>
    </restaurant>
    <restaurant>
        <name>Eatrenalin</name>
        <image>images/restaurants/eatrenalin.svg</image>
        <appearances>
            <appearance>
                <episode>8</episode>
                <episodeTime>13:57</episodeTime>
            </appearance>
        </appearances>
        <characteristics>
            <characteristic>
                <episode>8</episode>
                <episodeTime>14:08</episodeTime>
                <description>Restaurant im Europa-Park</description>
            </characteristic>
        </characteristics>
    </restaurant>
    <restaurant>
        <name>Café Wien Sylt</name>
        <image>images/restaurants/cafe_wien_sylt.svg</image>
        <appearances>
            <appearance>
                <episode>8</episode>
                <episodeTime>7:42</episodeTime>
            </appearance>
        </appearances>
    </restaurant>
    <restaurant>
        <name>Schwarzwaldstube (Traube Tonbach)</name>
        <image>images/restaurants/traube_tonbach.svg</image>
        <team>
            <member>Nina Mihilli</member>
        </team>
        <appearances>
            <appearance>
                <episode>7</episode>
                <episodeTime>2:46:05</episodeTime>
            </appearance>
        </appearances>
    </restaurant>
    <restaurant>
        <name>Frühstück 3000</name>
        <image>images/restaurants/fruestueck_3000.jpg</image>
        <appearances>
            <appearance>
                <episode>4</episode>
                <episodeTime>4:06:25</episodeTime>
            </appearance>
        </appearances>
    </restaurant>
    <restaurant>
        <name>PHP</name>
        <image>images/restaurants/php.jpeg</image>
        <appearances>
            <appearance>
                <episode>4</episode>
                <episodeTime>35:10</episodeTime>
            </appearance>
        </appearances>
    </restaurant>
    <restaurant>
        <name>Zollpackhof</name>
        <description>Peter's Lieblings-Biergarten.</description>
        <image>images/restaurants/zollpackhof.png</image>
        <appearances>
            <appearance>
                <episode>4</episode>
                <episodeTime>18:34</episodeTime>
            </appearance>
        </appearances>
        <characteristics>
            <characteristic>
                <episode>4</episode>
                <episodeTime>18:34</episodeTime>
                <description>Peter's Lieblings-Biergarten</description>
            </characteristic>
        </characteristics>
    </restaurant>
    <restaurant>
        <name>Café Frieda</name>
        <image>images/restaurants/cafe_frieda.jpg</image>
        <team>
            <member>Samina Raza</member>
            <member>Ben Zviel</member>
        </team>
        <appearances>
            <appearance>
                <episode>1</episode>
                <episodeType>bonus</episodeType>
                <episodeTime>00:11:54</episodeTime>
            </appearance>
            <appearance>
                <episode>1</episode>
                <episodeType>bonus</episodeType>
                <episodeTime>00:00:00</episodeTime>
            </appearance>
        </appearances>
        <characteristics>
            <characteristic>
                <episode>1</episode>
                <episodeType>bonus</episodeType>
                <episodeTime>00:06:31</episodeTime>
                <description>Zweitprojekt der Gründer des Mrs Robinson's</description>
            </characteristic>
            <characteristic>
                <episode>1</episode>
                <episodeType>bonus</episodeType>
                <episodeTime>00:06:10</episodeTime>
                <description>offene Küche</description>
            </characteristic>
        </characteristics>
    </restaurant>
    <restaurant>
        <name>Tim Raue</name>
        <image>images/restaurants/tim_raue.png</image>
        <team>
            <member>Tim Raue</member>
        </team>
        <appearances>
            <appearance>
                <episode>11</episode>
                <episodeTime>3:01:00</episodeTime>
            </appearance>
            <appearance>
                <episode>3</episode>
                <episodeTime>3:12:00</episodeTime>
            </appearance>
            <appearance>
                <episode>1</episode>
                <episodeTime>2:34:38</episodeTime>
            </appearance>
        </appearances>
    </restaurant>
    <restaurant>
        <name>MS Marone</name>
        <image>images/restaurants/ms_marone.png</image>
        <appearances>
            <appearance>
                <episode>31</episode>
                <episodeTime>2:01:15</episodeTime>
            </appearance>
            <appearance>
                <episode>1</episode>
                <episodeTime>1:17:18</episodeTime>
            </appearance>
        </appearances>
        <characteristics>
            <characteristic>
                <episode>1</episode>
                <episodeTime>1:17:18</episodeTime>
                <description>macht unglaublich leckere Hollandaise-Sauce</description>
            </characteristic>
        </characteristics>
    </restaurant>
    <restaurant>
        <name>tulus lotrek</name>
        <image>images/restaurants/tulus_lotrek.jpg</image>
        <team>
            <member>Ilona Scholl</member>
            <member>Max Strohe</member>
            <member>Felix Fuchs</member>
        </team>
        <appearances>
            <appearance>
                <episode>30</episode>
                <episodeTime>2:48:28</episodeTime>
            </appearance>
            <appearance>
                <episode>15</episode>
                <episodeTime>2:09:00</episodeTime>
            </appearance>
            <appearance>
                <episode>1</episode>
                <episodeTime>00:01:40</episodeTime>
            </appearance>
        </appearances>
        <characteristics>
            <characteristic>
                <episode>2</episode>
                <episodeTime>21:14</episodeTime>
                <description>Restaurant Nr. 1 in Berlin 2022 vom Ehepaar Smits</description>
            </characteristic>
            <characteristic>
                <episode>1</episode>
                <episodeTime>00:20:52</episodeTime>
                <description>bestes Serviceteam 2022 vom Feinschmecker</description>
            </characteristic>
            <characteristic>
                <episode>1</episode>
                <episodeTime>00:14:37</episodeTime>
                <description>ganz viele Hauben vom Gault Milleau</description>
            </characteristic>
            <characteristic>
                <episode>1</episode>
                <episodeTime>00:14:37</episodeTime>
                <description>1x Stern vom Guide Michelin</description>
            </characteristic>
            <characteristic>
                <episode>1</episode>
                <episodeTime>00:13:46</episodeTime>
                <description>2015 von Ilona Scholl und Max Strohe gegründet</description>
            </characteristic>
        </characteristics>
    </restaurant>
</root>